ShareDB/ShareDB.py
ShareDB/__init__.py
ShareDB-1.1.4.dist-info/LICENSE
ShareDB-1.1.4.dist-info/METADATA
ShareDB-1.1.4.dist-info/WHEEL
ShareDB-1.1.4.dist-info/top_level.txt
ShareDB-1.1.4.dist-info/RECORD
