Metadata-Version: 2.1
Name: ShareDB
Version: 1.1.4
Summary: An on-disk pythonic embedded key-value store for compressed data storage and distributed data analysis.
Home-page: https://github.com/ayaanhossain/ShareDB
Author: Ayaan Hossain
Author-email: auh57@psu.edu
Project-URL: Bug Reports, https://github.com/ayaanhossain/ShareDB/issues
Project-URL: Source, https://github.com/ayaanhossain/ShareDB/
Keywords: lmdb embedded key value store parallel data share read multiprocessing db
Classifier: Development Status :: 4 - Beta
Classifier: Intended Audience :: Developers
Classifier: Intended Audience :: Science/Research
Classifier: Topic :: Database
Classifier: License :: OSI Approved :: MIT License
Classifier: Programming Language :: Python :: 2.7
Classifier: Programming Language :: Python :: 3.6
Classifier: Programming Language :: Python :: 3.7
Classifier: Programming Language :: Python :: 3.8
Classifier: Programming Language :: Python :: 3.9
Classifier: Programming Language :: Python :: 3.10
Classifier: Programming Language :: Python :: 3.11
Classifier: Programming Language :: Python :: 3.12
Requires-Python: >=2.7, !=3.0.*, !=3.1.*, !=3.2.*, !=3.3.*, !=3.4.*, !=3.5.*, <4
License-File: LICENSE
Requires-Dist: lmdb >=0.98
Requires-Dist: msgpack >=0.6.2
Requires-Dist: configparser >=4.0.2
Requires-Dist: pytest-cov >=2.8.1
